LICENSE.txt
README.md
setup.cfg
setup.py
PyWGCNA/__init__.py
PyWGCNA/comparison.py
PyWGCNA/geneExp.py
PyWGCNA/utils.py
PyWGCNA/wgcna.py
PyWGCNA.egg-info/PKG-INFO
PyWGCNA.egg-info/SOURCES.txt
PyWGCNA.egg-info/dependency_links.txt
PyWGCNA.egg-info/requires.txt
PyWGCNA.egg-info/top_level.txt